opentf/operator/main.py
opentf_agent_operator_nightly-0.1.0.dev110.dist-info/LICENSE
opentf_agent_operator_nightly-0.1.0.dev110.dist-info/METADATA
opentf_agent_operator_nightly-0.1.0.dev110.dist-info/WHEEL
opentf_agent_operator_nightly-0.1.0.dev110.dist-info/top_level.txt
opentf_agent_operator_nightly-0.1.0.dev110.dist-info/RECORD
