Metadata-Version: 2.1
Name: opentf-agent-operator-nightly
Version: 0.1.0.dev110
Summary: OpenTestFactory Orchestrator Agent Operator
Home-page: https://opentestfactory.org/guides/agent-operator.html
Author: Martin Lafaix
Author-email: mlafaix@henix.com
Maintainer: Henix
Maintainer-email: opentestfactory@henix.com
License: Apache Software License (https://www.apache.org/licenses/LICENSE-2.0)
Classifier: Development Status :: 3 - Alpha
Classifier: Programming Language :: Python :: 3
Classifier: Operating System :: OS Independent
Classifier: Topic :: Software Development :: Libraries
Classifier: License :: OSI Approved :: Apache Software License
Requires-Python: >= 3.10.0
License-File: LICENSE
Requires-Dist: requests >=2.25
Requires-Dist: kopf >=1.37
Requires-Dist: kubernetes >=29.0.0
